rubricgenerator_mcp_server/__init__.py
rubricgenerator_mcp_server/agent.py
rubricgenerator_mcp_server/chains.py
rubricgenerator_mcp_server/nodes.py
rubricgenerator_mcp_server/rubric_app.py
rubricgenerator_mcp_server/server.py
rubricgenerator_mcp_server/state.py
rubricgenerator_mcp_server/tools.py
rubricgenerator_mcp-0.1.1.dist-info/METADATA
rubricgenerator_mcp-0.1.1.dist-info/WHEEL
rubricgenerator_mcp-0.1.1.dist-info/top_level.txt
rubricgenerator_mcp-0.1.1.dist-info/RECORD
